pydiscordwrapper/__init__.py
pydiscordwrapper/_client.py
pydiscordwrapper/_endpoints.py
pydiscordwrapper/_urls.py
pydiscordwrapper/types/AuthToken.py
pydiscordwrapper/types/Channel.py
pydiscordwrapper/types/Emoji.py
pydiscordwrapper/types/Guild.py
pydiscordwrapper/types/Member.py
pydiscordwrapper/types/Role.py
pydiscordwrapper/types/User.py
pydiscordwrapper/types/__init__.py
pydiscordwrapper-0.1.5.dist-info/LICENSE
pydiscordwrapper-0.1.5.dist-info/WHEEL
pydiscordwrapper-0.1.5.dist-info/METADATA
pydiscordwrapper-0.1.5.dist-info/RECORD
